soft_test/__init__.py
soft_test/cli.py
soft_test-0.1.0.dist-info/entry_points.txt
soft_test-0.1.0.dist-info/WHEEL
soft_test-0.1.0.dist-info/METADATA
soft_test-0.1.0.dist-info/RECORD
