Metadata-Version: 2.1
Name: soft-test
Version: 0.1.0
Summary: 
Author: elbulidur
Author-email: juliocezar.marketing@gmail.com
Requires-Python: >=3.9,<4.0
Classifier: Programming Language :: Python :: 3
Classifier: Programming Language :: Python :: 3.9
Classifier: Programming Language :: Python :: 3.10
Classifier: Programming Language :: Python :: 3.11
Requires-Dist: httpx (>=0.23.0,<0.24.0)
Requires-Dist: kivy (>=2.1.0,<3.0.0)
Requires-Dist: kivymd (>=1.1.1,<2.0.0)
